[
  {
    "id": 2169,
    "title": "Count Operations to Obtain Zero",
    "difficulty": "Easy",
    "acceptanceRate": 74.9,
    "frequency": 100,
    "url": "https://leetcode.com/problems/count-operations-to-obtain-zero",
    "tags": [],
    "isPremium": false
  },
  {
    "id": 424,
    "title": "Longest Repeating Character Replacement",
    "difficulty": "Medium",
    "acceptanceRate": 57.4,
    "frequency": 62.5,
    "url": "https://leetcode.com/problems/longest-repeating-character-replacement",
    "tags": [],
    "isPremium": false
  }
]