[
  {
    "id": 20,
    "title": "Valid Parentheses",
    "difficulty": "Easy",
    "acceptanceRate": 42.4,
    "frequency": 100,
    "url": "https://leetcode.com/problems/valid-parentheses",
    "tags": [],
    "isPremium": false
  },
  {
    "id": 412,
    "title": "Fizz Buzz",
    "difficulty": "Easy",
    "acceptanceRate": 74.5,
    "frequency": 87.5,
    "url": "https://leetcode.com/problems/fizz-buzz",
    "tags": [],
    "isPremium": false
  },
  {
    "id": 78,
    "title": "Subsets",
    "difficulty": "Medium",
    "acceptanceRate": 81,
    "frequency": 87.5,
    "url": "https://leetcode.com/problems/subsets",
    "tags": [],
    "isPremium": false
  },
  {
    "id": 1,
    "title": "Two Sum",
    "difficulty": "Easy",
    "acceptanceRate": 55.9,
    "frequency": 87.5,
    "url": "https://leetcode.com/problems/two-sum",
    "tags": [],
    "isPremium": false
  },
  {
    "id": 242,
    "title": "Valid Anagram",
    "difficulty": "Easy",
    "acceptanceRate": 66.8,
    "frequency": 87.5,
    "url": "https://leetcode.com/problems/valid-anagram",
    "tags": [],
    "isPremium": false
  },
  {
    "id": 11,
    "title": "Container With Most Water",
    "difficulty": "Medium",
    "acceptanceRate": 57.9,
    "frequency": 87.5,
    "url": "https://leetcode.com/problems/container-with-most-water",
    "tags": [],
    "isPremium": false
  },
  {
    "id": 48,
    "title": "Rotate Image",
    "difficulty": "Medium",
    "acceptanceRate": 78.1,
    "frequency": 87.5,
    "url": "https://leetcode.com/problems/rotate-image",
    "tags": [],
    "isPremium": false
  }
]